zoldyck/__init__.py
zoldyck/messengerBot/__init__.py
zoldyck/messengerBot/messenger.py
zoldyck/messengerBot/handlers/__init__.py
zoldyck/messengerBot/handlers/jsonHandler.py
zoldyck/messengerBot/structure/__init__.py
zoldyck/messengerBot/structure/buttons.py
zoldyck/messengerBot/structure/quickReplies.py
zoldyck/messengerBot/structure/simpleMsg.py
zoldyck/messengerBot/structure/templates.py
zoldyck-1.1.dist-info/METADATA
zoldyck-1.1.dist-info/RECORD
zoldyck-1.1.dist-info/WHEEL
zoldyck-1.1.dist-info/top_level.txt
